meteoswiss_async/__init__.py
meteoswiss_async/client.py
meteoswiss_async/errors.py
meteoswiss_async/model.py
meteoswiss_async-0.1.1.dist-info/LICENSE
meteoswiss_async-0.1.1.dist-info/WHEEL
meteoswiss_async-0.1.1.dist-info/METADATA
meteoswiss_async-0.1.1.dist-info/RECORD
